check_if_nan/LICENSE
check_if_nan/README.MD
check_if_nan/__init__.py
check_if_nan/requirements.txt
check_if_nan/thirdparty.json
check_if_nan-0.11.dist-info/LICENSE.rst
check_if_nan-0.11.dist-info/METADATA
check_if_nan-0.11.dist-info/WHEEL
check_if_nan-0.11.dist-info/top_level.txt
check_if_nan-0.11.dist-info/RECORD
