Metadata-Version: 2.1
Name: check-if-nan
Version: 0.11
Summary: Checks for all kinds of nan/None values without raising Exceptions all the time
Home-page: https://github.com/hansalemaos/check_if_nan
Author: Johannes Fischer
Author-email: aulasparticularesdealemaosp@gmail.com
License: MIT
Keywords: nan,None
Classifier: Development Status :: 4 - Beta
Classifier: Programming Language :: Python :: 3 :: Only
Classifier: Programming Language :: Python :: 3.10
Classifier: Topic :: Software Development :: Libraries :: Python Modules
Classifier: Topic :: Utilities
License-File: LICENSE.rst
Requires-Dist: disable-warnings
Requires-Dist: numpy
Requires-Dist: pandas
